puzzle_arcade_server/__init__.py
puzzle_arcade_server/constants.py
puzzle_arcade_server/eval.py
puzzle_arcade_server/gym_env.py
puzzle_arcade_server/server.py
puzzle_arcade_server/export/__init__.py
puzzle_arcade_server/export/dataset.py
puzzle_arcade_server/games/__init__.py
puzzle_arcade_server/games/_base/__init__.py
puzzle_arcade_server/games/_base/commands.py
puzzle_arcade_server/games/_base/game.py
puzzle_arcade_server/games/binary/__init__.py
puzzle_arcade_server/games/binary/config.py
puzzle_arcade_server/games/binary/game.py
puzzle_arcade_server/games/bridges/__init__.py
puzzle_arcade_server/games/bridges/config.py
puzzle_arcade_server/games/bridges/game.py
puzzle_arcade_server/games/einstein/__init__.py
puzzle_arcade_server/games/einstein/config.py
puzzle_arcade_server/games/einstein/constants.py
puzzle_arcade_server/games/einstein/game.py
puzzle_arcade_server/games/einstein/models.py
puzzle_arcade_server/games/fillomino/__init__.py
puzzle_arcade_server/games/fillomino/config.py
puzzle_arcade_server/games/fillomino/game.py
puzzle_arcade_server/games/futoshiki/__init__.py
puzzle_arcade_server/games/futoshiki/config.py
puzzle_arcade_server/games/futoshiki/game.py
puzzle_arcade_server/games/hidato/__init__.py
puzzle_arcade_server/games/hidato/config.py
puzzle_arcade_server/games/hidato/game.py
puzzle_arcade_server/games/hitori/__init__.py
puzzle_arcade_server/games/hitori/config.py
puzzle_arcade_server/games/hitori/game.py
puzzle_arcade_server/games/kakuro/__init__.py
puzzle_arcade_server/games/kakuro/config.py
puzzle_arcade_server/games/kakuro/game.py
puzzle_arcade_server/games/kenken/__init__.py
puzzle_arcade_server/games/kenken/config.py
puzzle_arcade_server/games/kenken/enums.py
puzzle_arcade_server/games/kenken/game.py
puzzle_arcade_server/games/kenken/models.py
puzzle_arcade_server/games/killer_sudoku/__init__.py
puzzle_arcade_server/games/killer_sudoku/config.py
puzzle_arcade_server/games/killer_sudoku/game.py
puzzle_arcade_server-0.8.dist-info/METADATA
puzzle_arcade_server-0.8.dist-info/WHEEL
puzzle_arcade_server-0.8.dist-info/entry_points.txt
puzzle_arcade_server-0.8.dist-info/top_level.txt
puzzle_arcade_server-0.8.dist-info/RECORD
