Metadata-Version: 2.4
Name: puzzle-arcade-server
Version: 0.8
Summary: Multi-game puzzle server for telnet - LLMs with MCP solvers welcome!
Author: Chris Hay
License: MIT
Project-URL: Homepage, https://github.com/chrishayuk/puzzle-arcade-server
Project-URL: Repository, https://github.com/chrishayuk/puzzle-arcade-server
Project-URL: Documentation, https://github.com/chrishayuk/puzzle-arcade-server#readme
Keywords: puzzle,telnet,server,game,sudoku,kenken,kakuro,websocket,mcp
Classifier: Development Status :: 3 - Alpha
Classifier: Intended Audience :: Developers
Classifier: Programming Language :: Python :: 3
Classifier: Programming Language :: Python :: 3.11
Classifier: Programming Language :: Python :: 3.12
Requires-Python: >=3.11
Requires-Dist: chuk-gym-core>=0.1.1
Requires-Dist: chuk-protocol-server>=0.1.0
Requires-Dist: pydantic>=2.0.0
Provides-Extra: dev
Requires-Dist: pytest>=7.4.0; extra == "dev"
Requires-Dist: pytest-cov>=4.1.0; extra == "dev"
Requires-Dist: pytest-asyncio>=0.21.0; extra == "dev"
Requires-Dist: pytest-watch>=4.2.0; extra == "dev"
Requires-Dist: ruff>=0.1.0; extra == "dev"
Requires-Dist: mypy>=1.4.0; extra == "dev"
Requires-Dist: bandit>=1.7.5; extra == "dev"
Requires-Dist: websockets>=11.0.0; extra == "dev"
Requires-Dist: ipython>=8.14.0; extra == "dev"
